pysyslimit/__init__.py
pysyslimit/api/__init__.py
pysyslimit/api/base.py
pysyslimit/api/group/__init__.py
pysyslimit/api/group/groupadd.py
pysyslimit/api/group/groupdel.py
pysyslimit/api/permission/__init__.py
pysyslimit/api/permission/chmod.py
pysyslimit/api/user/__init__.py
pysyslimit/api/user/chown.py
pysyslimit/api/user/useradd.py
pysyslimit/api/user/userdel.py
pysyslimit/config/__init__.py
pysyslimit/config/meta.py
pysyslimit/models/__init__.py
pysyslimit/models/permission/__init__.py
pysyslimit/models/permission/full.py
pysyslimit/models/permission/single.py
pysyslimit/models/user/__init__.py
pysyslimit/models/user/group.py
pysyslimit/models/user/user.py
pysyslimit/utils/__init__.py
pysyslimit/utils/execute.py
pysyslimit-0.5.0.dist-info/LICENSE
pysyslimit-0.5.0.dist-info/METADATA
pysyslimit-0.5.0.dist-info/WHEEL
pysyslimit-0.5.0.dist-info/top_level.txt
pysyslimit-0.5.0.dist-info/RECORD
