Metadata-Version: 2.1
Name: pysyslimit
Version: 0.5.0
Summary: Python library which can manage linux permissions.
Home-page: https://github.com/pysyslimit-dev/pysyslimit
Author: HansBug, PotassiumWings
Author-email: hansbug@buaa.edu.cn, potassium@buaa.edu.cn
License: Apache License, Version 2.0
Keywords: Python library which can manage linux permissions.
Platform: UNKNOWN
Classifier: Development Status :: 5 - Production/Stable
Classifier: Intended Audience :: Developers
Classifier: License :: OSI Approved :: Apache Software License
Classifier: Programming Language :: Python
Classifier: Programming Language :: Python :: 3
Classifier: Programming Language :: Python :: 3.6
Classifier: Programming Language :: Python :: 3.7
Classifier: Programming Language :: Python :: 3.8
Classifier: Programming Language :: Python :: 3.9
Classifier: Programming Language :: Python :: 3.10
Requires-Python: >=3.6
License-File: LICENSE
Requires-Dist: where (>=1)
Provides-Extra: doc
Requires-Dist: sphinx (~=3.2.0) ; extra == 'doc'
Requires-Dist: sphinx-rtd-theme (~=0.4.3) ; extra == 'doc'
Requires-Dist: enum-tools ; extra == 'doc'
Requires-Dist: sphinx-toolbox ; extra == 'doc'
Requires-Dist: plantumlcli (>=0.0.2) ; extra == 'doc'
Requires-Dist: packaging ; extra == 'doc'
Requires-Dist: sphinx-multiversion (~=0.2.4) ; extra == 'doc'
Requires-Dist: where (~=1.0.2) ; extra == 'doc'
Requires-Dist: easydict (<2,>=1.7) ; extra == 'doc'
Provides-Extra: test
Requires-Dist: coverage (>=5) ; extra == 'test'
Requires-Dist: mock (>=4.0.3) ; extra == 'test'
Requires-Dist: flake8 (~=3.5) ; extra == 'test'
Requires-Dist: pytest (~=6.2.5) ; extra == 'test'
Requires-Dist: pytest-cov (~=3.0.0) ; extra == 'test'
Requires-Dist: pytest-mock (~=3.6.1) ; extra == 'test'
Requires-Dist: pytest-xdist (>=1.34.0) ; extra == 'test'
Requires-Dist: pytest-rerunfailures (~=10.2) ; extra == 'test'
Requires-Dist: pytest-timeout (~=2.0.2) ; extra == 'test'
Requires-Dist: where (>=1.0.2) ; extra == 'test'
